[
  {
    "type": "admissions_empty",
    "year": 2021,
    "province_id": 11,
    "province": "北京",
    "source": "admissions"
  },
  {
    "type": "admissions_empty",
    "year": 2021,
    "province_id": 31,
    "province": "上海",
    "source": "admissions"
  },
  {
    "type": "admissions_empty",
    "year": 2021,
    "province_id": 42,
    "province": "湖北",
    "source": "admissions"
  },
  {
    "type": "admissions_empty",
    "year": 2021,
    "province_id": 43,
    "province": "湖南",
    "source": "admissions"
  },
  {
    "type": "admissions_empty",
    "year": 2022,
    "province_id": 11,
    "province": "北京",
    "source": "admissions"
  },
  {
    "type": "admissions_empty",
    "year": 2022,
    "province_id": 31,
    "province": "上海",
    "source": "admissions"
  },
  {
    "type": "admissions_empty",
    "year": 2023,
    "province_id": 11,
    "province": "北京",
    "source": "admissions"
  },
  {
    "type": "admissions_empty",
    "year": 2023,
    "province_id": 31,
    "province": "上海",
    "source": "admissions"
  },
  {
    "type": "admissions_empty",
    "year": 2023,
    "province_id": 42,
    "province": "湖北",
    "source": "admissions"
  },
  {
    "type": "admissions_empty",
    "year": 2023,
    "province_id": 43,
    "province": "湖南",
    "source": "admissions"
  },
  {
    "type": "admissions_empty",
    "year": 2025,
    "province_id": 44,
    "province": "广东",
    "source": "admissions"
  },
  {
    "type": "admissions_empty",
    "year": 2025,
    "province_id": 11,
    "province": "北京",
    "source": "admissions"
  },
  {
    "type": "admissions_empty",
    "year": 2025,
    "province_id": 31,
    "province": "上海",
    "source": "admissions"
  },
  {
    "type": "admissions_empty",
    "year": 2025,
    "province_id": 32,
    "province": "江苏",
    "source": "admissions"
  },
  {
    "type": "admissions_empty",
    "year": 2025,
    "province_id": 42,
    "province": "湖北",
    "source": "admissions"
  },
  {
    "type": "admissions_empty",
    "year": 2025,
    "province_id": 43,
    "province": "湖南",
    "source": "admissions"
  },
  {
    "type": "admissions_empty",
    "year": 2025,
    "province_id": 51,
    "province": "四川",
    "source": "admissions"
  },
  {
    "type": "admissions_empty",
    "year": 2025,
    "province_id": 41,
    "province": "河南",
    "source": "admissions"
  },
  {
    "type": "major_list_failed",
    "message": "Could not fetch major list from zsb.scnu.edu.cn",
    "source": "curriculum"
  },
  {
    "type": "reports_not_found",
    "message": "Could not auto-discover employment report PDFs. Using published aggregate statistics instead.",
    "source": "employment"
  }
]